{
  "மேஷம்": "உங்கள் முயற்சிகள் இன்றைய தினம் சிறந்த பலன்களை தரும். பணியிலும் தனிப்பட்ட உறவுகளிலும் தெளிவான முடிவுகளை எடுக்க வாய்ப்பு உள்ளது. ஆரோக்கியம் குறித்த கவனத்தை அதிகரிக்க வேண்டிய அவசரம் உள்ளது, சிறிய மாற்றங்கள் நன்மை தரும்.",
  "ரிஷபம்": "நிதி நிலைமை அதிகரிக்க வாய்ப்பு உள்ளது; புதிய முதலீடுகளில் கவனமாக இருக்க வேண்டும். குடும்பத்தில் சில மாறுதல்கள் ஏற்படலாம், அதனால் பொறுமையாக நடந்து கொள்ள வேண்டும். வேலை தொடர்பான சிக்கல்களைத் திறம்பட சமாளிக்க முடியும்.",
  "மிதுனம்": "இன்று உங்கள் அறிவாற்றல் மிகுந்துவிடும், முக்கியமான பேச்சுவார்த்தைகளில் வெற்றி பெறலாம். பணியில் புதிய திட்டங்களை முன்மொழிய உண்டு; அதற்கு தலைவர்கள் ஆதரவு தருவர். உடல் நலம் சிறிது கவனிக்க வேண்டியதாகும்.",
  "கடகம்": "உயிரின் உறவுகள் மேம்படும், குடும்பத்துடன் நேரத்தை செலவிடுங்கள். பணியிலும் தனிப்பட்ட வாழ்விலும் அமைதி நிலவ வாய்ப்பு உள்ளது. புதிய வாய்ப்புகள் உங்கள் எதிர்காலத்தை பிரகாசமாக மாற்றும்.",
  "சிம்மம்": "இன்றைய நாள் காதல் மற்றும் உறவுகளுக்கு சிறந்தது. பணியிலும் பொருளாதாரத்தில் சீரான முன்னேற்றம் காணலாம். ஆரோக்கியம் சிறப்பாக இருக்கும், ஆனாலும் உணவு பழக்கங்களை கவனிக்க வேண்டியது முக்கியம்.",
  "கன்னி": "பணியில் அதிக முயற்சி தேவைப்படும் காலம்; தாமதங்கள் உண்டாகலாம். தனிப்பட்ட வாழ்க்கையில் உணர்ச்சிபூர்வ மாற்றங்கள் ஏற்பட வாய்ப்பு உள்ளது. நிதி விஷயங்களில் முறையாக திட்டமிடுங்கள்.",
  "துலாம்": "உங்கள் சமூகநிலையிலும் பணியிலும் புதிய சந்தர்ப்பங்கள் தோன்றும். உறவு சம்பந்தமான குழப்பங்கள் சமாளிக்கப்படலாம், நேர்மையுடன் நடந்து கொள்ளுங்கள். உடல் நலம் சிறிது கவனிக்க வேண்டும்.",
  "விருச்சிகம்": "ஆரம்பத்தில் சிக்கல்கள் இருந்தாலும், உங்கள் முயற்சி வெற்றிக்காக வழி அமைக்கும். பணியிலும் நிதியிலும் முன்னேற்றம் காணலாம். மனஅழுத்தம் குறைக்க மனத்தளர்ச்சி பயனுள்ளதாக இருக்கும்.",
  "தனுசு": "புதிய வேலை வாய்ப்புகள் உங்களை காத்திருக்கின்றன; அதற்கு தயாராக இருங்கள். குடும்பத்தில் மகிழ்ச்சி நிலவும், உறவுகளை வலுப்படுத்தும் நேரம். உடல் சக்தி அதிகரிக்கும், ஆனாலும் ஓய்வை பராமரிக்க வேண்டும்.",
  "மகரம்": "நிதி நிலைமை நிலைத்திருக்கும், தேவையான செலவுகளைச் சரியாக கட்டுப்படுத்துங்கள். பணியிலும் நண்பர்களுடனும் உறவு வலுவாகும். ஆரோக்கியத்தில் சிறிய மாற்றங்கள் நல்லது தரும்.",
  "கும்பம்": "சிறந்த தகவல்கள் மற்றும் அறிவுரைகள் உங்கள் முன்னேற்றத்திற்கு உதவும். உறவு பிரச்சினைகள் தீரும், புதிய நண்பர்கள் சேர வாய்ப்பு உள்ளது. உடல் நலம் சிறந்த நிலையில் இருக்கும்.",
  "மீனம்": "சனிக்கிழமை உங்களுக்கு கடுமையான பாடங்களை கற்றுத்தருகிறது; பொறுமையுடன் செயல்படவேண்டும். பணியில் தாமதங்கள் காணப்படலாம்; அதனால் கவலைப்பட வேண்டாம். குடும்ப உறவுகள் நெருக்கமடையும் நேரம்."
}